{
  "車両乗入れ": { "value": false, "note": "サイト内乗入れ可／1台500円" },
  "料金": {
    "オフシーズン": "3000円",
    "レギュラー": "4500円",
    "ハイシーズン": "6000円"
  },
  "設備・アメニティ": {
    "AC電源": { "value": false, "note": "1500Wまで／有料500円" },
    "水道栓": { "value": false, "note": "サイト横に共有蛇口" },
    "焚き火台設置可": { "value": false, "note": "焚き火シート必須" },
    "直火": { "value": false, "note": "専用ファイヤーピットのみ可" },
    "タープポール": { "value": false, "note": "無料貸出2本まで" },
    "ウッドデッキ": { "value": false, "note": "3×3m／ペグ禁止" },
    "テーブル／ベンチ": { "value": false, "note": "常設木製セットあり" },
    "ペット可": { "value": false, "note": "リード必須／大型犬不可" },
    "Wi-Fi": { "value": false, "note": "管理棟周辺のみ" }
  },
  "近接施設": {
    "炊事場距離_m": "30",
    "トイレ距離_m": "20",
    "ゴミ捨て場距離_m": "50",
    "シャワー距離_m": "100"
  },
  "サービスオプション": {
    "BBQグリル貸出": { "value": false, "note": "1台1500円／網付き" },
    "テントレンタル": { "value": false, "note": "4名用テント3000円" },
    "寝袋レンタル": { "value": false, "note": "3シーズン用／500円" },
    "朝食セット": { "value": false, "note": "パン・コーヒー／800円" },
    "夕食BBQセット": { "value": false, "note": "肉・野菜セット／2500円" }
  },
  "騒音・静粛時間": "22:00‑6:00は静粛時間",
  "ゴミ捨てルール": "分別必須／有料ゴミ袋100円",
  "備考": {
    "type": "textarea",
    "rows": 4,
    "note": "風が強いためペグは20cm以上さしてください。"
  }
}
